dbgsom/BaseSom.py
dbgsom/SomClassifier.py
dbgsom/SomVQ.py
dbgsom/__init__.py
dbgsom/dbgsom_.py
dbgsom/test_dbgsom_.py
dbgsom-1.1.0.dist-info/LICENSE.md
dbgsom-1.1.0.dist-info/METADATA
dbgsom-1.1.0.dist-info/WHEEL
dbgsom-1.1.0.dist-info/top_level.txt
dbgsom-1.1.0.dist-info/RECORD
