Metadata-Version: 2.1
Name: dbgsom
Version: 1.1.0
Summary: A Python implementation of the Directed Batch Growing Self-Organizing Map
Home-page: https://github.com/SandroMartens/DBGSOM
Author: Sandro Martens
Author-email: Sandro Martens <sandro.martens@web.de>
License: MIT
Project-URL: Homepage, https://github.com/SandroMartens/DBGSOM
Project-URL: Docmentation, https://dbgsom.readthedocs.io/en/latest/
Classifier: Programming Language :: Python :: 3
Classifier: License :: OSI Approved :: MIT License
Classifier: Operating System :: OS Independent
Requires-Python: >=3.9
License-File: LICENSE.md
Requires-Dist: numpy
Requires-Dist: networkx
Requires-Dist: pandas
Requires-Dist: seaborn
Requires-Dist: tqdm
Requires-Dist: scikit-learn
Requires-Dist: numpydoc
